Products.PloneKeywordManager-6.0.0-py3.10-nspkg.pth
Products/PloneKeywordManager/__init__.py
Products/PloneKeywordManager/build_translations.sh
Products/PloneKeywordManager/compat.py
Products/PloneKeywordManager/config.py
Products/PloneKeywordManager/configure.zcml
Products/PloneKeywordManager/interfaces.py
Products/PloneKeywordManager/keysearch.ico
Products/PloneKeywordManager/setuphandlers.py
Products/PloneKeywordManager/testing.py
Products/PloneKeywordManager/tool.py
Products/PloneKeywordManager/upgrades.py
Products/PloneKeywordManager/upgrades.zcml
Products/PloneKeywordManager/browser/__init__.py
Products/PloneKeywordManager/browser/configure.zcml
Products/PloneKeywordManager/browser/interfaces.py
Products/PloneKeywordManager/browser/prefs_keywords_view.pt
Products/PloneKeywordManager/browser/prefs_keywords_view.py
Products/PloneKeywordManager/locales/Products.PloneKeywordManager.pot
Products/PloneKeywordManager/locales/da/LC_MESSAGES/Products.PloneKeywordManager.po
Products/PloneKeywordManager/locales/de/LC_MESSAGES/Products.PloneKeywordManager.po
Products/PloneKeywordManager/locales/fr/LC_MESSAGES/Products.PloneKeywordManager.po
Products/PloneKeywordManager/locales/he/LC_MESSAGES/Products.PloneKeywordManager.po
Products/PloneKeywordManager/locales/it/LC_MESSAGES/Products.PloneKeywordManager.po
Products/PloneKeywordManager/locales/nl/LC_MESSAGES/Products.PloneKeywordManager.po
Products/PloneKeywordManager/locales/pt/LC_MESSAGES/Products.PloneKeywordManager.po
Products/PloneKeywordManager/locales/pt_BR/LC_MESSAGES/Products.PloneKeywordManager.po
Products/PloneKeywordManager/profiles/default/browserlayer.xml
Products/PloneKeywordManager/profiles/default/controlpanel.xml
Products/PloneKeywordManager/profiles/default/keywords.txt
Products/PloneKeywordManager/profiles/default/metadata.xml
Products/PloneKeywordManager/profiles/default/rolemap.xml
Products/PloneKeywordManager/profiles/uninstall/browserlayer.xml
Products.PloneKeywordManager-6.0.0.dist-info/METADATA
Products.PloneKeywordManager-6.0.0.dist-info/WHEEL
Products.PloneKeywordManager-6.0.0.dist-info/entry_points.txt
Products.PloneKeywordManager-6.0.0.dist-info/namespace_packages.txt
Products.PloneKeywordManager-6.0.0.dist-info/top_level.txt
Products.PloneKeywordManager-6.0.0.dist-info/RECORD
