Metadata-Version: 2.1
Name: Products.PloneKeywordManager
Version: 6.0.0
Summary: Change, merge and delete keywords (subjects) in Plone.
Home-page: https://github.com/collective/Products.PloneKeywordManager
Author: Maik Jabolnski, Michael Dunlap and the Plone collective
Author-email: dunlapm@u.washington.edu
License: GNU General Public License v2 (GPLv2)
Keywords: plone,manage keywords subjects create merge delete
Classifier: Development Status :: 6 - Mature
Classifier: Environment :: Web Environment
Classifier: Framework :: Plone
Classifier: Framework :: Plone :: 6.0
Classifier: Framework :: Plone :: Addon
Classifier: Intended Audience :: End Users/Desktop
Classifier: Intended Audience :: System Administrators
Classifier: License :: OSI Approved :: GNU General Public License v2 (GPLv2)
Classifier: Operating System :: OS Independent
Classifier: Programming Language :: Python
Classifier: Programming Language :: Python :: 3.8
Classifier: Programming Language :: Python :: 3.9
Classifier: Programming Language :: Python :: 3.10
Classifier: Programming Language :: Python :: 3.11
Classifier: Topic :: Software Development :: Libraries :: Python Modules
Requires-Dist: plone.api
Requires-Dist: setuptools
Provides-Extra: levenshtein
Requires-Dist: python-Levenshtein ; extra == 'levenshtein'
Provides-Extra: dev
Requires-Dist: pdbpp ; extra == 'dev'
Provides-Extra: test
Requires-Dist: plone.app.testing ; extra == 'test'
Requires-Dist: plone.app.contenttypes[test] ; extra == 'test'
